README.md
setup.cfg
setup.py
tb1_parser/__init__.py
tb1_parser/_ai_sheet_parser.py
tb1_parser/_di_sheet_parser.py
tb1_parser/_do_sheet_parser.py
tb1_parser/_regex_lib.py
tb1_parser/_sheet_parser.py
tb1_parser/_tb1_file_reader.py
tb1_parser/_tb1_readed_sheets_collection.py
tb1_parser/_tb1_sheet_reader.py
tb1_parser/ai_signal.py
tb1_parser/di_signal.py
tb1_parser/do_signal.py
tb1_parser/parsed_tb1_collection.py
tb1_parser/plc_module.py
tb1_parser/signal.py
tb1_parser/signals_collection.py
tb1_parser/tb1_parser.py
tb1_parser.egg-info/PKG-INFO
tb1_parser.egg-info/SOURCES.txt
tb1_parser.egg-info/dependency_links.txt
tb1_parser.egg-info/not-zip-safe
tb1_parser.egg-info/requires.txt
tb1_parser.egg-info/top_level.txt