Metadata-Version: 2.1
Name: tb1_parser
Version: 1.0.9
Summary: ТБ1 парсер
Home-page: https://github.com/ss3nclam/tb1_parser
Author: ss3n_clam
Author-email: glebrodionov1993@gmail.com
Requires-Dist: openpyxl
Requires-Dist: xlrd
Requires-Dist: pandas
Requires-Dist: transliterate
